registry.json
src/__init__.py
src/main.py
src/commands/__init__.py
src/commands/add.py
src/commands/init.py
src/commands/list.py
src/utils/__init__.py
src/utils/manifetGen.py
bds_mcbe-0.1.0.dist-info/METADATA
bds_mcbe-0.1.0.dist-info/WHEEL
bds_mcbe-0.1.0.dist-info/entry_points.txt
bds_mcbe-0.1.0.dist-info/licenses/LICENSE
bds_mcbe-0.1.0.dist-info/RECORD
